unet_lungs_segmentation/__init__.py
unet_lungs_segmentation/cli.py
unet_lungs_segmentation/lungs_predict.py
unet_lungs_segmentation/model.py
unet_lungs_segmentation/napari.yaml
unet_lungs_segmentation/utils.py
unet_lungs_segmentation/napari_plugin/__init__.py
unet_lungs_segmentation/napari_plugin/plugin.py
unet_lungs_segmentation-1.0.9.dist-info/LICENSE
unet_lungs_segmentation-1.0.9.dist-info/METADATA
unet_lungs_segmentation-1.0.9.dist-info/WHEEL
unet_lungs_segmentation-1.0.9.dist-info/entry_points.txt
unet_lungs_segmentation-1.0.9.dist-info/top_level.txt
unet_lungs_segmentation-1.0.9.dist-info/RECORD
