Metadata-Version: 2.1
Name: unet-lungs-segmentation
Version: 1.0.9
Summary: 3D U-Net model for the segmentation of the lungs in mice CT scans.
Home-page: https://github.com/qchapp/lungs-segmentation.git
Author: Quentin Chappuis, Center for Imaging, Ecole Polytechnique Federale de Lausanne (EPFL)
Author-email: quentin.chappuis@epfl.ch
License: BSD-3-Clause
Project-URL: Source Code, https://github.com/qchapp/lungs-segmentation.git
Classifier: Development Status :: 2 - Pre-Alpha
Classifier: Framework :: napari
Classifier: Intended Audience :: Developers
Classifier: License :: OSI Approved :: BSD License
Classifier: Operating System :: OS Independent
Classifier: Programming Language :: Python
Classifier: Programming Language :: Python :: 3
Classifier: Programming Language :: Python :: 3.8
Classifier: Programming Language :: Python :: 3.9
Classifier: Programming Language :: Python :: 3.10
Classifier: Topic :: Scientific/Engineering :: Image Processing
Requires-Python: >=3.8
License-File: LICENSE
Requires-Dist: magicgui
Requires-Dist: qtpy
Requires-Dist: napari[all]>=0.4.16
Requires-Dist: napari-label-focus
Requires-Dist: tifffile
Requires-Dist: scikit-image
Requires-Dist: matplotlib
Requires-Dist: csbdeep
Requires-Dist: python-dotenv
Requires-Dist: huggingface-hub
Provides-Extra: testing
Requires-Dist: tox; extra == "testing"
Requires-Dist: pytest; extra == "testing"
Requires-Dist: pytest-cov; extra == "testing"
Requires-Dist: pytest-qt; extra == "testing"
Requires-Dist: napari; extra == "testing"
Requires-Dist: pyqt5; extra == "testing"
